Lab8/class/demux.v
module demux (
    input [3:0] Data,
    input [1:0] SEL,
    input Enable,
    output [3:0] lib, [3:0] fd, [3:0] sch, [3:0] rib
);

    assign lib = ((SEL == 'b00) ? Data : 4'b0000);
    assign fd  = ((SEL == 'b01) ? Data : 4'b0000);
    assign sch = ((SEL == 'b10) ? Data : 4'b0000);
    assign rib = ((SEL == 'b11) ? Data : 4'b0000);

endmodule

Lab8/class/mux.v
module mux (
    input [3:0] CEO, [3:0] self, [3:0] Fred, [3:0] Jill,
    input [1:0] SEL,
    input Enable,
    output [3:0] Data
);

    assign Data = (SEL == 'b00 ? CEO :
                    SEL == 'b01 ? self :
                    SEL == 'b10 ? Fred : Jill) & {4{Enable}};
    
endmodule

Lab8/class/top.v
module top (
    input [15:0] sw,
    input btnC, btnU, btnR, btnD, btnL,
    output [15:0] led
);
    wire [1:0] muxSEL;
    assign muxSEL = {btnU, btnL};
    
    wire [1:0] demuxSEL;
    assign demuxSEL = {btnR, btnD};
    
    wire [3:0] bus;
    
    mux sourceIP (
        .CEO(sw[3:0]),
        .self(sw[7:4]),
        .Fred(sw[11:8]),
        .Jill(sw[15:12]),
        .SEL(muxSEL),
        .Enable(btnC),
        .Data(bus)
    );
    
    demux destIP (
        .Data(bus),
        .SEL(demuxSEL),
        .Enable(btnC),
        .lib(led[3:0]),
        .fd(led[7:4]),
        .sch(led[11:8]),
        .rib(led[15:12])
    );
    
endmodule

Lab8/class/test.v
`timescale 1ns/1ps

module test();
    wire [15:0] led;
    reg [15:0] sw;
    reg btnl, btnu, btnd, btnr, btnc;

    top uut(
        .led(led),
        .sw(sw),
        .btnL(btnl),
        .btnU(btnu),
        .btnD(btnd),
        .btnR(btnr),
        .btnC(btnc)
    );

    reg [4:0] i;
    
    wire [1:0] mult_sel;
    wire [1:0] demult_sel;
    
    wire [3:0] current_mult;
    wire [3:0] current_demult;
    
    assign mult_sel = {btnu, btnl};
    assign demult_sel = {btnr, btnd};
    
    assign current_mult = (sw >> (4 * mult_sel)) & 'hF;
    assign current_demult = (led  >> (4 * demult_sel)) & 'hF;

    initial begin
        $dumpvars(0, test);
        sw = 'b0110_1010_0101_1001;
        btnl = 0;
        btnu = 0;
        btnd = 0;
        btnr = 0;
        btnc = 0;
        #10;
        btnc = 1;
        for (i = 0; i < 16; i = i + 1) begin
            #10;
            btnl = i[0];
            btnu = i[1];
            btnd = i[2];
            btnr = i[3];
            
            if (current_mult != current_demult) begin
                // If your simulation stops here
                // then your design fails the test!
                $display("Failed test!");
                $finish;
            end
        end
        #10 $finish;
    end
endmodule

Lab8/MuxAndDemux/MuxAndDemux.sim/sim_1/behav/xsim/dump.vcd
$date
   Sun Mar  9 15:33:24 2025
$end

$version
  2024.2.0
$end

$timescale
  1ps
$end

$scope module test $end
$var wire 16 ! led [15:0] $end
$var reg 16 " sw [15:0] $end
$var reg 1 # btnl $end
$var reg 1 $ btnu $end
$var reg 1 % btnd $end
$var reg 1 & btnr $end
$var reg 1 ' btnc $end
$var reg 5 ( i [4:0] $end
$var wire 2 ) mult_sel [1:0] $end
$var wire 2 * demult_sel [1:0] $end
$var wire 4 + current_mult [3:0] $end
$var wire 4 , current_demult [3:0] $end
$scope module uut $end
$var wire 16 - sw [15:0] $end
$var wire 1 . btnC $end
$var wire 1 / btnU $end
$var wire 1 0 btnR $end
$var wire 1 1 btnD $end
$var wire 1 2 btnL $end
$var wire 16 ! led [15:0] $end
$var wire 2 3 muxSEL [1:0] $end
$var wire 2 4 demuxSEL [1:0] $end
$var wire 4 5 bus [3:0] $end
$scope module sourceIP $end
$var wire 4 6 CEO [3:0] $end
$var wire 4 7 self [7:4] $end
$var wire 4 8 Fred [11:8] $end
$var wire 4 9 Jill [15:12] $end
$var wire 2 3 SEL [1:0] $end
$var wire 1 . Enable $end
$var wire 4 5 Data [3:0] $end
$upscope $end
$scope module destIP $end
$var wire 4 5 Data [3:0] $end
$var wire 2 4 SEL [1:0] $end
$var wire 1 . Enable $end
$var wire 4 : lib [3:0] $end
$var wire 4 ; fd [7:4] $end
$var wire 4 < sch [11:8] $end
$var wire 4 = rib [15:12] $end
$upscope $end
$upscope $end
$upscope $end
$enddefinitions $end

#0
$dumpvars
b0 !
b110101001011001 "
0#
0$
0%
0&
0'
bx (
b0 )
b0 *
b1001 +
b0 ,
b110101001011001 -
0.
0/
00
01
02
b0 3
b0 4
b0 5
b1001 6
b101 7
b1010 8
b110 9
b0 :
b0 ;
b0 <
b0 =
$end

#10000
b1001 !
1'
b0 (
b1001 ,
1.
b1001 5
b1001 :

#20000
b1 (

#30000
b101 !
1#
b10 (
b1 )
b101 +
b101 ,
12
b1 3
b101 5
b101 :

#40000
b1010 !
0#
1$
b11 (
b10 )
b1010 +
b1010 ,
1/
02
b10 3
b1010 5
b1010 :

#50000
b110 !
1#
b100 (
b11 )
b110 +
b110 ,
12
b11 3
b110 5
b110 :

#60000
b10010000 !
0#
0$
1%
b101 (
b0 )
b1 *
b1001 +
b1001 ,
0/
11
02
b0 3
b1 4
b1001 5
b0 :
b1001 ;

#70000
b1010000 !
1#
b110 (
b1 )
b101 +
b101 ,
12
b1 3
b101 5
b101 ;

#80000
b10100000 !
0#
1$
b111 (
b10 )
b1010 +
b1010 ,
1/
02
b10 3
b1010 5
b1010 ;

#90000
b1100000 !
1#
b1000 (
b11 )
b110 +
b110 ,
12
b11 3
b110 5
b110 ;

#100000
b100100000000 !
0#
0$
0%
1&
b1001 (
b0 )
b10 *
b1001 +
b1001 ,
0/
10
01
02
b0 3
b10 4
b1001 5
b0 ;
b1001 <

#110000
b10100000000 !
1#
b1010 (
b1 )
b101 +
b101 ,
12
b1 3
b101 5
b101 <

#120000
b101000000000 !
0#
1$
b1011 (
b10 )
b1010 +
b1010 ,
1/
02
b10 3
b1010 5
b1010 <

#130000
b11000000000 !
1#
b1100 (
b11 )
b110 +
b110 ,
12
b11 3
b110 5
b110 <

#140000
b1001000000000000 !
0#
0$
1%
b1101 (
b0 )
b11 *
b1001 +
b1001 ,
0/
11
02
b0 3
b11 4
b1001 5
b0 <
b1001 =

#150000
b101000000000000 !
1#
b1110 (
b1 )
b101 +
b101 ,
12
b1 3
b101 5
b101 =

#160000
b1010000000000000 !
0#
1$
b1111 (
b10 )
b1010 +
b1010 ,
1/
02
b10 3
b1010 5
b1010 =

#170000
b110000000000000 !
1#
b10000 (
b11 )
b110 +
b110 ,
12
b11 3
b110 5
b110 =
