Lab10/class/tff.v
module tff(
    input T, E,
    output reg Q,
    output NotQ
);

    initial begin
        Q <= 0;
    end
    
    always @(posedge E) begin
        if (T)
            Q <= ~Q;
    end
    
    assign NotQ = ~Q;

endmodule

Lab10/class/dff.v
module dff(
    input D, E,
    output reg Q,
    output NotQ
);

    initial begin
        Q <= 0;
    end
    
    always @(posedge E) begin
        Q <= D;
    end
    
    assign NotQ = ~Q;

endmodule

Lab10/class/jkff.v
module jkff (
    input J, K, E,
    output Q,
    output NotQ
);

    reg D;

    always @(J, K, E) begin
        if (J && K)
            case(Q)
                0: D <= 1;
                1: D <= 0;
            endcase
        else if (J)
            D <= 1;
        else if (K)
            D <= 0;
        else
            D <= Q;
     end
     
     
     dff DFF (
        .D(D),
        .E(E),
        .Q(Q),
        .NotQ(NotQ)
     );

endmodule

Lab10/class/top.v
module top (
    input [3:0] sw,
    input btnC,
    output [5:0] led
);

    dff D (
        .D(sw[0]),
        .E(btnC),
        .Q(led[0]),
        .NotQ(led[1])
    );
    
    jkff JK (
        .J(sw[1]),
        .K(sw[2]),
        .E(btnC),
        .Q(led[2]),
        .NotQ(led[3])
    );
    
    tff T (
        .T(sw[3]),
        .E(btnC),
        .Q(led[4]),
        .NotQ(led[5])
    );

endmodule

Lab10/class/test.v
module test();
    reg [3:0] sw;
    reg btnC;
    wire [5:0] led;

    top uut(
        .sw(sw),
        .led(led),
        .btnC(btnC)
    );

    task automatic toggle_clock;
        begin
            #1 btnC = 1;
            #1 btnC = 0;
        end
    endtask

    task automatic set_check_dff(input D, input ExpectedQ);
        begin
            sw[0] = D;
            toggle_clock();
            if (led[0] != ExpectedQ || led[1] == ExpectedQ) begin
                $display("D FF test failed: expected Q = %b, ~Q = %b got %b | %b", ExpectedQ, ~ExpectedQ, led[0], led[1]);
            end
        end
    endtask

    task automatic set_check_jkff(input J, input K, input ExpectedQ);
        begin
            sw[1] = J;
            sw[2] = K;
            toggle_clock();
            if (led[2] != ExpectedQ || led[3] == ExpectedQ) begin
                $display("JK FF test failed: expected Q = %b, ~Q = %b got %b | %b", ExpectedQ, ~ExpectedQ, led[2], led[3]);
            end
        end
    endtask

    task automatic set_check_tff(input T, input ExpectedQ);
        begin
            sw[3] = T;
            toggle_clock();
            if (led[4] != ExpectedQ || led[5] == ExpectedQ) begin
                $display("JK FF test failed: expected Q = %b, ~Q = %b got %b | %b", ExpectedQ, ~ExpectedQ, led[4], led[5]);
            end
        end
    endtask

    initial begin
        $dumpvars(0,test);
        btnC = 0;
        sw = 4'b0;
        toggle_clock();
        
        set_check_dff(0, 0);
        set_check_dff(1, 1);

        set_check_jkff(0, 1, 0);
        set_check_jkff(0, 0, 0);
        set_check_jkff(1, 0, 1);
        set_check_jkff(0, 0, 1);
        set_check_jkff(1, 1, 0);
        set_check_jkff(1, 1, 1);

        set_check_tff(0, 0);
        set_check_tff(1, 1);
        set_check_tff(0, 1);
        set_check_tff(1, 0);
    end

endmodule

Lab10/edgesencir/edgesencir.sim/sim_1/behav/xsim/dump.vcd
$date
   Mon Mar 31 21:53:02 2025
$end

$version
  2024.2.0
$end

$timescale
  1ps
$end

$scope module test $end
$var reg 4 ! sw [3:0] $end
$var reg 1 " btnC $end
$var wire 6 # led [5:0] $end
$scope module uut $end
$var wire 4 $ sw [3:0] $end
$var wire 1 % btnC $end
$var wire 6 # led [5:0] $end
$scope module D $end
$var wire 1 & D $end
$var wire 1 % E $end
$var reg 1 ' Q $end
$var wire 1 ( NotQ $end
$upscope $end
$scope module JK $end
$var wire 1 ) J $end
$var wire 1 * K $end
$var wire 1 % E $end
$var wire 1 + Q $end
$var wire 1 , NotQ $end
$var reg 1 - D $end
$scope module DFF $end
$var wire 1 . D $end
$var wire 1 % E $end
$var reg 1 / Q $end
$var wire 1 , NotQ $end
$upscope $end
$upscope $end
$scope module T $end
$var wire 1 0 T $end
$var wire 1 % E $end
$var reg 1 1 Q $end
$var wire 1 2 NotQ $end
$upscope $end
$upscope $end
$scope task toggle_clock $end
$upscope $end
$scope task set_check_dff $end
$upscope $end
$scope task set_check_jkff $end
$upscope $end
$scope task set_check_tff $end
$upscope $end
$upscope $end
$enddefinitions $end

#0
$dumpvars
b0 !
0"
b101010 #
b0 $
0%
0&
0'
1(
0)
0*
0+
1,
x-
x.
0/
00
01
12
$end

#1000
1"
b10xx10 #
1%
x+
x,
0-
0.
x/

#2000
0"
0%
x-
x.

#3000
1"
1%

#4000
b1 !
0"
b1 $
0%
1&
0)
0*
00

#5000
1"
b10xx01 #
1%
1'
0(

#6000
b101 !
0"
b101 $
0%
1&
0)
1*
0-
0.
00

#7000
1"
b101001 #
1%
0+
1,
0/

#8000
b1 !
0"
b1 $
0%
1&
0)
0*
00

#9000
1"
1%

#10000
b11 !
0"
b11 $
0%
1&
1)
0*
1-
1.
00

#11000
1"
b100101 #
1%
1+
0,
1/

#12000
b1 !
0"
b1 $
0%
1&
0)
0*
00

#13000
1"
1%

#14000
b111 !
0"
b111 $
0%
1&
1)
1*
0-
0.
00

#15000
1"
b101001 #
1%
0+
1,
0/

#16000
0"
0%
1-
1.

#17000
1"
b100101 #
1%
1+
0,
1/

#18000
0"
0%
0-
0.

#19000
1"
b101001 #
1%
0+
1,
0/

#20000
b1111 !
0"
b1111 $
0%
1&
1)
1*
1-
1.
10

#21000
1"
b10101 #
1%
1+
0,
1/
11
02

#22000
b111 !
0"
b111 $
0%
1&
1)
1*
0-
0.
00

#23000
1"
b11001 #
1%
0+
1,
0/

#24000
b1111 !
0"
b1111 $
0%
1&
1)
1*
1-
1.
10

#25000
1"
b100101 #
1%
1+
0,
1/
01
12

#26000
0"
0%
0-
0.
