Lab7/DelaysAndGlitches/DelaysAndGlitches.sim/sim_1/impl/timing/xsim/test_time_impl.v
// Copyright 1986-2022 Xilinx, Inc. All Rights Reserved.
// Copyright 2022-2024 Advanced Micro Devices, Inc. All Rights Reserved.
// --------------------------------------------------------------------------------
// Tool Version: Vivado v.2024.2 (lin64) Build 5239630 Fri Nov 08 22:34:34 MST 2024
// Date        : Sun Feb 23 15:06:38 2025
// Host        : luis-UX461UA running 64-bit Ubuntu 24.04.1 LTS
// Command     : write_verilog -mode timesim -nolib -sdf_anno true -force -file
//               /home/luis/Documents/BSU/ECE230L/Lab7/DelaysAndGlitches/DelaysAndGlitches.sim/sim_1/impl/timing/xsim/test_time_impl.v
// Design      : top
// Purpose     : This verilog netlist is a timing simulation representation of the design and should not be modified or
//               synthesized. Please ensure that this netlist is used with the corresponding SDF file.
// Device      : xc7a35tcpg236-1
// --------------------------------------------------------------------------------
`timescale 1 ps / 1 ps
`define XIL_TIMING

(* ECO_CHECKSUM = "e3acf4b8" *) 
(* NotValidForBitStream *)
(* \DesignAttr:ENABLE_NOC_NETLIST_VIEW  *) 
(* \DesignAttr:ENABLE_AIE_NETLIST_VIEW  *) 
module top
   (sw,
    led);
  input [15:0]sw;
  output [15:0]led;

  wire [15:0]led;
  wire [15:0]led_OBUF;
  wire [15:0]sw;
  wire [15:0]sw_IBUF;

initial begin
 $sdf_annotate("test_time_impl.sdf",,,,"tool_control");
end
  OBUF \led_OBUF[0]_inst 
       (.I(led_OBUF[0]),
        .O(led[0]));
  LUT1 #(
    .INIT(2'h1)) 
    \led_OBUF[0]_inst_i_1 
       (.I0(sw_IBUF[0]),
        .O(led_OBUF[0]));
  OBUF \led_OBUF[10]_inst 
       (.I(led_OBUF[10]),
        .O(led[10]));
  LUT6 #(
    .INIT(64'h6996966996696996)) 
    \led_OBUF[10]_inst_i_1 
       (.I0(sw_IBUF[10]),
        .I1(sw_IBUF[8]),
        .I2(sw_IBUF[6]),
        .I3(led_OBUF[5]),
        .I4(sw_IBUF[7]),
        .I5(sw_IBUF[9]),
        .O(led_OBUF[10]));
  OBUF \led_OBUF[11]_inst 
       (.I(led_OBUF[11]),
        .O(led[11]));
  (* SOFT_HLUTNM = "soft_lutpair3" *) 
  LUT2 #(
    .INIT(4'h6)) 
    \led_OBUF[11]_inst_i_1 
       (.I0(sw_IBUF[11]),
        .I1(led_OBUF[10]),
        .O(led_OBUF[11]));
  OBUF \led_OBUF[12]_inst 
       (.I(led_OBUF[12]),
        .O(led[12]));
  (* SOFT_HLUTNM = "soft_lutpair3" *) 
  LUT3 #(
    .INIT(8'h96)) 
    \led_OBUF[12]_inst_i_1 
       (.I0(sw_IBUF[12]),
        .I1(led_OBUF[10]),
        .I2(sw_IBUF[11]),
        .O(led_OBUF[12]));
  OBUF \led_OBUF[13]_inst 
       (.I(led_OBUF[13]),
        .O(led[13]));
  (* SOFT_HLUTNM = "soft_lutpair0" *) 
  LUT4 #(
    .INIT(16'h6996)) 
    \led_OBUF[13]_inst_i_1 
       (.I0(sw_IBUF[13]),
        .I1(sw_IBUF[11]),
        .I2(led_OBUF[10]),
        .I3(sw_IBUF[12]),
        .O(led_OBUF[13]));
  OBUF \led_OBUF[14]_inst 
       (.I(led_OBUF[14]),
        .O(led[14]));
  (* SOFT_HLUTNM = "soft_lutpair0" *) 
  LUT5 #(
    .INIT(32'h96696996)) 
    \led_OBUF[14]_inst_i_1 
       (.I0(sw_IBUF[14]),
        .I1(sw_IBUF[12]),
        .I2(led_OBUF[10]),
        .I3(sw_IBUF[11]),
        .I4(sw_IBUF[13]),
        .O(led_OBUF[14]));
  OBUF \led_OBUF[15]_inst 
       (.I(led_OBUF[15]),
        .O(led[15]));
  LUT6 #(
    .INIT(64'h6996966996696996)) 
    \led_OBUF[15]_inst_i_1 
       (.I0(sw_IBUF[15]),
        .I1(sw_IBUF[13]),
        .I2(sw_IBUF[11]),
        .I3(led_OBUF[10]),
        .I4(sw_IBUF[12]),
        .I5(sw_IBUF[14]),
        .O(led_OBUF[15]));
  OBUF \led_OBUF[1]_inst 
       (.I(led_OBUF[1]),
        .O(led[1]));
  (* SOFT_HLUTNM = "soft_lutpair5" *) 
  LUT2 #(
    .INIT(4'h9)) 
    \led_OBUF[1]_inst_i_1 
       (.I0(sw_IBUF[1]),
        .I1(sw_IBUF[0]),
        .O(led_OBUF[1]));
  OBUF \led_OBUF[2]_inst 
       (.I(led_OBUF[2]),
        .O(led[2]));
  (* SOFT_HLUTNM = "soft_lutpair5" *) 
  LUT3 #(
    .INIT(8'h69)) 
    \led_OBUF[2]_inst_i_1 
       (.I0(sw_IBUF[2]),
        .I1(sw_IBUF[0]),
        .I2(sw_IBUF[1]),
        .O(led_OBUF[2]));
  OBUF \led_OBUF[3]_inst 
       (.I(led_OBUF[3]),
        .O(led[3]));
  (* SOFT_HLUTNM = "soft_lutpair2" *) 
  LUT4 #(
    .INIT(16'h9669)) 
    \led_OBUF[3]_inst_i_1 
       (.I0(sw_IBUF[3]),
        .I1(sw_IBUF[1]),
        .I2(sw_IBUF[0]),
        .I3(sw_IBUF[2]),
        .O(led_OBUF[3]));
  OBUF \led_OBUF[4]_inst 
       (.I(led_OBUF[4]),
        .O(led[4]));
  (* SOFT_HLUTNM = "soft_lutpair2" *) 
  LUT5 #(
    .INIT(32'h69969669)) 
    \led_OBUF[4]_inst_i_1 
       (.I0(sw_IBUF[4]),
        .I1(sw_IBUF[2]),
        .I2(sw_IBUF[0]),
        .I3(sw_IBUF[1]),
        .I4(sw_IBUF[3]),
        .O(led_OBUF[4]));
  OBUF \led_OBUF[5]_inst 
       (.I(led_OBUF[5]),
        .O(led[5]));
  LUT6 #(
    .INIT(64'h9669699669969669)) 
    \led_OBUF[5]_inst_i_1 
       (.I0(sw_IBUF[5]),
        .I1(sw_IBUF[3]),
        .I2(sw_IBUF[1]),
        .I3(sw_IBUF[0]),
        .I4(sw_IBUF[2]),
        .I5(sw_IBUF[4]),
        .O(led_OBUF[5]));
  OBUF \led_OBUF[6]_inst 
       (.I(led_OBUF[6]),
        .O(led[6]));
  (* SOFT_HLUTNM = "soft_lutpair4" *) 
  LUT2 #(
    .INIT(4'h6)) 
    \led_OBUF[6]_inst_i_1 
       (.I0(sw_IBUF[6]),
        .I1(led_OBUF[5]),
        .O(led_OBUF[6]));
  OBUF \led_OBUF[7]_inst 
       (.I(led_OBUF[7]),
        .O(led[7]));
  (* SOFT_HLUTNM = "soft_lutpair4" *) 
  LUT3 #(
    .INIT(8'h96)) 
    \led_OBUF[7]_inst_i_1 
       (.I0(sw_IBUF[7]),
        .I1(led_OBUF[5]),
        .I2(sw_IBUF[6]),
        .O(led_OBUF[7]));
  OBUF \led_OBUF[8]_inst 
       (.I(led_OBUF[8]),
        .O(led[8]));
  (* SOFT_HLUTNM = "soft_lutpair1" *) 
  LUT4 #(
    .INIT(16'h6996)) 
    \led_OBUF[8]_inst_i_1 
       (.I0(sw_IBUF[8]),
        .I1(sw_IBUF[6]),
        .I2(led_OBUF[5]),
        .I3(sw_IBUF[7]),
        .O(led_OBUF[8]));
  OBUF \led_OBUF[9]_inst 
       (.I(led_OBUF[9]),
        .O(led[9]));
  (* SOFT_HLUTNM = "soft_lutpair1" *) 
  LUT5 #(
    .INIT(32'h96696996)) 
    \led_OBUF[9]_inst_i_1 
       (.I0(sw_IBUF[9]),
        .I1(sw_IBUF[7]),
        .I2(led_OBUF[5]),
        .I3(sw_IBUF[6]),
        .I4(sw_IBUF[8]),
        .O(led_OBUF[9]));
  IBUF \sw_IBUF[0]_inst 
       (.I(sw[0]),
        .O(sw_IBUF[0]));
  IBUF \sw_IBUF[10]_inst 
       (.I(sw[10]),
        .O(sw_IBUF[10]));
  IBUF \sw_IBUF[11]_inst 
       (.I(sw[11]),
        .O(sw_IBUF[11]));
  IBUF \sw_IBUF[12]_inst 
       (.I(sw[12]),
        .O(sw_IBUF[12]));
  IBUF \sw_IBUF[13]_inst 
       (.I(sw[13]),
        .O(sw_IBUF[13]));
  IBUF \sw_IBUF[14]_inst 
       (.I(sw[14]),
        .O(sw_IBUF[14]));
  IBUF \sw_IBUF[15]_inst 
       (.I(sw[15]),
        .O(sw_IBUF[15]));
  IBUF \sw_IBUF[1]_inst 
       (.I(sw[1]),
        .O(sw_IBUF[1]));
  IBUF \sw_IBUF[2]_inst 
       (.I(sw[2]),
        .O(sw_IBUF[2]));
  IBUF \sw_IBUF[3]_inst 
       (.I(sw[3]),
        .O(sw_IBUF[3]));
  IBUF \sw_IBUF[4]_inst 
       (.I(sw[4]),
        .O(sw_IBUF[4]));
  IBUF \sw_IBUF[5]_inst 
       (.I(sw[5]),
        .O(sw_IBUF[5]));
  IBUF \sw_IBUF[6]_inst 
       (.I(sw[6]),
        .O(sw_IBUF[6]));
  IBUF \sw_IBUF[7]_inst 
       (.I(sw[7]),
        .O(sw_IBUF[7]));
  IBUF \sw_IBUF[8]_inst 
       (.I(sw[8]),
        .O(sw_IBUF[8]));
  IBUF \sw_IBUF[9]_inst 
       (.I(sw[9]),
        .O(sw_IBUF[9]));
endmodule
`ifndef GLBL
`define GLBL
`timescale  1 ps / 1 ps

module glbl ();

    parameter ROC_WIDTH = 100000;
    parameter TOC_WIDTH = 0;
    parameter GRES_WIDTH = 10000;
    parameter GRES_START = 10000;

//--------   STARTUP Globals --------------
    wire GSR;
    wire GTS;
    wire GWE;
    wire PRLD;
    wire GRESTORE;
    tri1 p_up_tmp;
    tri (weak1, strong0) PLL_LOCKG = p_up_tmp;

    wire PROGB_GLBL;
    wire CCLKO_GLBL;
    wire FCSBO_GLBL;
    wire [3:0] DO_GLBL;
    wire [3:0] DI_GLBL;
   
    reg GSR_int;
    reg GTS_int;
    reg PRLD_int;
    reg GRESTORE_int;

//--------   JTAG Globals --------------
    wire JTAG_TDO_GLBL;
    wire JTAG_TCK_GLBL;
    wire JTAG_TDI_GLBL;
    wire JTAG_TMS_GLBL;
    wire JTAG_TRST_GLBL;

    reg JTAG_CAPTURE_GLBL;
    reg JTAG_RESET_GLBL;
    reg JTAG_SHIFT_GLBL;
    reg JTAG_UPDATE_GLBL;
    reg JTAG_RUNTEST_GLBL;

    reg JTAG_SEL1_GLBL = 0;
    reg JTAG_SEL2_GLBL = 0 ;
    reg JTAG_SEL3_GLBL = 0;
    reg JTAG_SEL4_GLBL = 0;

    reg JTAG_USER_TDO1_GLBL = 1'bz;
    reg JTAG_USER_TDO2_GLBL = 1'bz;
    reg JTAG_USER_TDO3_GLBL = 1'bz;
    reg JTAG_USER_TDO4_GLBL = 1'bz;

    assign (strong1, weak0) GSR = GSR_int;
    assign (strong1, weak0) GTS = GTS_int;
    assign (weak1, weak0) PRLD = PRLD_int;
    assign (strong1, weak0) GRESTORE = GRESTORE_int;

    initial begin
	GSR_int = 1'b1;
	PRLD_int = 1'b1;
	#(ROC_WIDTH)
	GSR_int = 1'b0;
	PRLD_int = 1'b0;
    end

    initial begin
	GTS_int = 1'b1;
	#(TOC_WIDTH)
	GTS_int = 1'b0;
    end

    initial begin 
	GRESTORE_int = 1'b0;
	#(GRES_START);
	GRESTORE_int = 1'b1;
	#(GRES_WIDTH);
	GRESTORE_int = 1'b0;
    end

endmodule
`endif

Lab7/class/test.v
`timescale 1ns/1ps

module test();

    reg [15:0] sw;
    wire [15:0] led;

    top uut(
        .led(led),
        .sw(sw)
    );

    initial begin
        $dumpvars(0,test);
        sw = 1'h0000;
        #16;
        if (led != 16'hffff) $display("Test failed!");
        sw = 16'hFFFF;
        #16
        if (led != 16'haaaa) $display("Test failed!");
        $finish;
    end

endmodule

Lab7/DelaysAndGlitches/DelaysAndGlitches.sim/sim_1/impl/timing/xsim/dump.vcd
$date
   Sun Feb 23 15:06:51 2025
$end

$version
  2024.2.0
$end

$timescale
  1ps
$end

$scope module test $end
$var reg 16 ! sw [15:0] $end
$var wire 16 " led [15:0] $end
$scope module uut $end
$var wire 16 " led [15:0] $end
$var wire 16 # led_OBUF [15:0] $end
$var wire 16 $ sw [15:0] $end
$var wire 16 % sw_IBUF [15:0] $end
$upscope $end
$upscope $end
$enddefinitions $end

#0
$dumpvars
b0 !
bx "
bx #
b0 $
bx %
$end

#1448
bx0xxx %

#1449
bx0xx0xxx %

#1450
bx0x00xxx %

#1452
bx111 #
b0 %

#1571
bx1x111 #

#1576
bx11111111 #

#1700
bx111x111111111 #

#1726
bx1111111111111 #

#1819
bx11111111111111 #

#1824
b1111111111111111 #

#4952
bx1xx "

#4955
bx111 "

#5075
bx1xxxx111 "

#5078
bx1xx1x111 "

#5081
bx11x1x111 "

#5084
bx11x11111 "

#5089
bx11111111 "

#5202
bx1xxx11111111 "

#5203
bx1xx111111111 "

#5217
bx11xx111111111 "

#5224
bx111x111111111 "

#5233
bx1111111111111 "

#5325
bx11111111111111 "

#5338
bx111111111111111 "

#5344
b1111111111111111 "

#15000
b1111111111111111 !
b1111111111111111 $

#16448
b1000 %

#16449
b1111111100111111 #
b1001000 %

#16450
b1011000 %

#16452
b1111011110111010 #
b1111111111111111 %

#16572
b1111011101010010 #

#16573
b1110101001010010 #

#16574
b1110101010110010 #

#16576
b100101010111010 #

#16600
b100101010101010 #

#16692
b110101010101010 #

#16696
b111011110101010 #

#16697
b1011011110101010 #

#16698
b1010101010101010 #

#16722
b1010100010101010 #

#16724
b1010101010101010 #

#16815
b1000101010101010 #

#16817
b1010101010101010 #

#16820
b110101010101010 #

#16822
b1010101010101010 #

#19948
b1111111101111111 "

#19951
b1111111111111111 "

#19952
b1111111111111011 "

#19954
b1111011110111011 "

#19955
b1111011110111010 "

#20071
b1111011100111010 "

#20073
b1111011110111010 "

#20075
b1111111110111010 "

#20076
b1111111010111010 "

#20077
b1111111011111010 "

#20079
b1111111010111010 "

#20080
b1111111010110010 "

#20082
b1101111010110010 "

#20084
b1101111010111010 "

#20085
b1101111010011010 "

#20087
b1101111010111010 "

#20090
b1100111010111010 "

#20096
b100111010111010 "

#20097
b100101010111010 "

#20107
b100101010101010 "

#20198
b110001010101010 "

#20199
b110001110101010 "

#20200
b110101110101010 "

#20201
b110101010101010 "

#20211
b10101010101010 "

#20213
b11101010101010 "

#20215
b10101010101010 "

#20217
b1010101010101010 "

#20220
b1010111010101010 "

#20222
b1010101010101010 "

#20229
b1010100010101010 "

#20231
b1010101010101010 "

#20321
b1000101010101010 "

#20323
b1010101010101010 "

#20334
b1110101010101010 "

#20336
b1010101010101010 "

#20340
b10101010101010 "

#20342
b1010101010101010 "
